<?xml version="1.0" encoding="utf-8" ?>
<XnaContent>
  <Asset Type="System.String[]">
    <Item>Sprites/Powerups/TestPowerup.png	{1, 1}</Item>
    <Item>WalkDown	100	R1	Looped</Item>
    <Item>WalkLeft	100	R1	Looped</Item>
    <Item>WalkRight	100	R1	Looped</Item>
    <Item>WalkUp	100	R1	Looped</Item>
    <Item>IdleDown	200	{1, 1}	{1, 1}	Default	Looped</Item>
    <Item>IdleLeft	200	{1, 1}	{1, 1}	Looped</Item>
    <Item>IdleRight	200	{1, 1}	{1, 1}	Looped</Item>
    <Item>IdleUp	200	{1, 1}	{1, 1}	Looped</Item>
  </Asset>
</XnaContent>
